odoo/addons/account_statement_import_file/README.rst
odoo/addons/account_statement_import_file/__init__.py
odoo/addons/account_statement_import_file/__manifest__.py
odoo/addons/account_statement_import_file/demo/partner_bank.xml
odoo/addons/account_statement_import_file/i18n/account_statement_import_file.pot
odoo/addons/account_statement_import_file/i18n/af.po
odoo/addons/account_statement_import_file/i18n/am.po
odoo/addons/account_statement_import_file/i18n/ar.po
odoo/addons/account_statement_import_file/i18n/az.po
odoo/addons/account_statement_import_file/i18n/bg.po
odoo/addons/account_statement_import_file/i18n/bs.po
odoo/addons/account_statement_import_file/i18n/ca.po
odoo/addons/account_statement_import_file/i18n/cs.po
odoo/addons/account_statement_import_file/i18n/da.po
odoo/addons/account_statement_import_file/i18n/de.po
odoo/addons/account_statement_import_file/i18n/el.po
odoo/addons/account_statement_import_file/i18n/en_AU.po
odoo/addons/account_statement_import_file/i18n/en_GB.po
odoo/addons/account_statement_import_file/i18n/es.po
odoo/addons/account_statement_import_file/i18n/es_AR.po
odoo/addons/account_statement_import_file/i18n/es_BO.po
odoo/addons/account_statement_import_file/i18n/es_CL.po
odoo/addons/account_statement_import_file/i18n/es_CO.po
odoo/addons/account_statement_import_file/i18n/es_CR.po
odoo/addons/account_statement_import_file/i18n/es_DO.po
odoo/addons/account_statement_import_file/i18n/es_EC.po
odoo/addons/account_statement_import_file/i18n/es_PE.po
odoo/addons/account_statement_import_file/i18n/es_PY.po
odoo/addons/account_statement_import_file/i18n/es_VE.po
odoo/addons/account_statement_import_file/i18n/et.po
odoo/addons/account_statement_import_file/i18n/eu.po
odoo/addons/account_statement_import_file/i18n/fa.po
odoo/addons/account_statement_import_file/i18n/fi.po
odoo/addons/account_statement_import_file/i18n/fo.po
odoo/addons/account_statement_import_file/i18n/fr.po
odoo/addons/account_statement_import_file/i18n/fr_BE.po
odoo_addon_account_statement_import_file-19.0.1.0.0.2.dist-info/METADATA
odoo_addon_account_statement_import_file-19.0.1.0.0.2.dist-info/WHEEL
odoo_addon_account_statement_import_file-19.0.1.0.0.2.dist-info/top_level.txt
odoo_addon_account_statement_import_file-19.0.1.0.0.2.dist-info/RECORD
